setup.py
cart/__init__.py
cart/cart.py
cart/models.py
cart/tests.py
cart/views.py
cart/migrations/0001_initial.py
cart/migrations/__init__.py
yet_another_django_cart.egg-info/PKG-INFO
yet_another_django_cart.egg-info/SOURCES.txt
yet_another_django_cart.egg-info/dependency_links.txt
yet_another_django_cart.egg-info/top_level.txt