Metadata-Version: 1.1
Name: yet-another-django-cart
Version: 1.0.1
Summary: Django simple shopping cart, tests and south migrations included
Home-page: https://github.com/otaviosoares/django-cart
Author: Otávio Soares
Author-email: otaviokk@gmail.com
License: GNU v3
Platform: UNKNOWN
Classifier: Development Status :: 5 - Production/Stable
Classifier: Environment :: Web Environment
Classifier: Framework :: Django
Classifier: Intended Audience :: Developers
Classifier: License :: OSI Approved :: BSD License
Classifier: Operating System :: OS Independent
Classifier: Programming Language :: Python
Classifier: Topic :: Software Development :: Libraries :: Python Modules
